COPYRIGHT.txt
LICENSE.txt
README.rst
setup.cfg
setup.py
doc/SSHLibrary.html
src/SSHLibrary/__init__.py
src/SSHLibrary/abstractclient.py
src/SSHLibrary/client.py
src/SSHLibrary/config.py
src/SSHLibrary/javaclient.py
src/SSHLibrary/library.py
src/SSHLibrary/pythonclient.py
src/SSHLibrary/version.py
src/robotframework_sshlibrary_forwardagent.egg-info/PKG-INFO
src/robotframework_sshlibrary_forwardagent.egg-info/SOURCES.txt
src/robotframework_sshlibrary_forwardagent.egg-info/dependency_links.txt
src/robotframework_sshlibrary_forwardagent.egg-info/requires.txt
src/robotframework_sshlibrary_forwardagent.egg-info/top_level.txt