Metadata-Version: 1.1
Name: robotframework-sshlibrary-forwardagent
Version: 2.1.2.1
Summary: Robot Framework test library for SSH and SFTP
Home-page: https://github.com/junousia/SSHLibrary
Author: Jukka Nousiainen
Author-email: jukka.nousiainen@gmail.com
License: Apache License 2.0
Keywords: robotframework testing testautomation ssh sftp
Platform: any
Classifier: Development Status :: 5 - Production/Stable
Classifier: License :: OSI Approved :: Apache Software License
Classifier: Operating System :: OS Independent
Classifier: Programming Language :: Python
Classifier: Topic :: Software Development :: Testing
